capytaine/__init__.py
capytaine/__about__.py
capytaine/ui/__init__.py
capytaine/ui/rich.py
capytaine/ui/cli.py
capytaine/ui/vtk/mesh_viewer.py
capytaine/ui/vtk/__init__.py
capytaine/ui/vtk/animation.py
capytaine/ui/vtk/helpers.py
capytaine/ui/vtk/body_viewer.py
capytaine/green_functions/__init__.py
capytaine/green_functions/delhommeau.py
capytaine/green_functions/hams.py
capytaine/green_functions/abstract_green_function.py
capytaine/green_functions/FinGreen3D/test_program.f90
capytaine/green_functions/FinGreen3D/LICENSE
capytaine/green_functions/FinGreen3D/Makefile
capytaine/green_functions/FinGreen3D/README.md
capytaine/green_functions/FinGreen3D/FinGreen3D.f90
capytaine/green_functions/FinGreen3D/.gitignore
capytaine/green_functions/LiangWuNoblesse/test_program.f90
capytaine/green_functions/LiangWuNoblesse/LICENSE
capytaine/green_functions/LiangWuNoblesse/Makefile
capytaine/green_functions/LiangWuNoblesse/README.md
capytaine/green_functions/LiangWuNoblesse/.gitignore
capytaine/green_functions/LiangWuNoblesse/LiangWuNoblesseWaveTerm.f90
capytaine/green_functions/libs/Delhommeau_float64.cpython-38-darwin.so
capytaine/green_functions/libs/Delhommeau_float32.cpython-38-darwin.so
capytaine/green_functions/libs/__init__.py
capytaine/bodies/dofs.py
capytaine/bodies/bodies.py
capytaine/bodies/__init__.py
capytaine/bodies/predefined/rectangles.py
capytaine/bodies/predefined/spheres.py
capytaine/bodies/predefined/__init__.py
capytaine/bodies/predefined/cylinders.py
capytaine/tools/lru_cache.py
capytaine/tools/cache_on_disk.py
capytaine/tools/timer.py
capytaine/tools/__init__.py
capytaine/tools/deprecation_handling.py
capytaine/tools/optional_imports.py
capytaine/tools/symbolic_multiplication.py
capytaine/tools/lists_of_points.py
capytaine/tools/prony_decomposition.py
capytaine/bem/solver.py
capytaine/bem/engines.py
capytaine/bem/__init__.py
capytaine/bem/problems_and_results.py
capytaine/bem/airy_waves.py
capytaine-2.3.1.dist-info/RECORD
capytaine-2.3.1.dist-info/LICENSE
capytaine-2.3.1.dist-info/WHEEL
capytaine-2.3.1.dist-info/entry_points.txt
capytaine-2.3.1.dist-info/METADATA
