Metadata-Version: 2.1
Name: capytaine
Version: 2.3.1
Summary: Python BEM solver for linear potential flow, based on Nemoh
Author-Email: Matthieu Ancellin <matthieu.ancellin@mews-labs.com>
License:                     GNU GENERAL PUBLIC LICENSE
Classifier: Programming Language :: Python
Classifier: Programming Language :: Fortran
Classifier: Intended Audience :: Science/Research
Classifier: License :: OSI Approved :: GNU General Public License v3 or later (GPLv3+)
Classifier: Topic :: Scientific/Engineering
Project-URL: homepage, https://capytaine.org
Project-URL: repository, https://github.com/capytaine/capytaine
Requires-Python: >=3.8
Requires-Dist: numpy>=1.20; python_version >= "3.9"
Requires-Dist: numpy>=1.24; python_version == "3.8"
Requires-Dist: scipy
Requires-Dist: pandas<3,>=1.3
Requires-Dist: xarray
Requires-Dist: rich
Provides-Extra: optional
Requires-Dist: matplotlib; extra == "optional"
Requires-Dist: joblib>=1.3; extra == "optional"
Requires-Dist: meshio; extra == "optional"
Requires-Dist: netcdf4; extra == "optional"
Requires-Dist: vtk; extra == "optional"
